pymystiko_cli/__init__.py
pymystiko_cli/aws.py
pymystiko_cli/cli.py
pymystiko_cli/mystiko.py
pymystiko_cli-0.3.1.dist-info/entry_points.txt
pymystiko_cli-0.3.1.dist-info/WHEEL
pymystiko_cli-0.3.1.dist-info/METADATA
pymystiko_cli-0.3.1.dist-info/RECORD
