Metadata-Version: 2.1
Name: pymystiko-cli
Version: 0.3.1
Summary: 
Author: Daniel Clayton
Author-email: dan@azwebmaster.com
Requires-Python: >=3.8,<4.0
Classifier: Programming Language :: Python :: 3
Classifier: Programming Language :: Python :: 3.8
Classifier: Programming Language :: Python :: 3.9
Requires-Dist: boto3 (>=1.17.75,<2.0.0)
Requires-Dist: click (>=8.0.0,<9.0.0)
